maxfw/__init__.py
maxfw/core/__init__.py
maxfw/core/api.py
maxfw/core/app.py
maxfw/core/default_config.py
maxfw/core/utils.py
maxfw/model/__init__.py
maxfw/model/model.py
maxfw/utils/__init__.py
maxfw/utils/image_functions.py
maxfw/utils/image_utils.py
maxfw-1.1.6.dist-info/LICENSE
maxfw-1.1.6.dist-info/METADATA
maxfw-1.1.6.dist-info/WHEEL
maxfw-1.1.6.dist-info/top_level.txt
maxfw-1.1.6.dist-info/zip-safe
maxfw-1.1.6.dist-info/RECORD
