Metadata-Version: 2.1
Name: maxfw
Version: 1.1.6
Summary: A package to simplify the creation of MAX models
Home-page: https://github.com/IBM/MAX-Framework
Author: CODAIT
Author-email: djalova@us.ibm.com, nickp@za.ibm.com, brendan.dwyer@ibm.com
License: Apache
Platform: UNKNOWN
Requires-Dist: flask-restx (>=0.3)
Requires-Dist: flask-cors (>=3.0.9)
Requires-Dist: Pillow (>=8.1.1)
Requires-Dist: numpy (>=1.18.4)
